uflux/__init__.py
uflux/uflux.py
uflux-0.0.1.dist-info/METADATA
uflux-0.0.1.dist-info/WHEEL
uflux-0.0.1.dist-info/top_level.txt
uflux-0.0.1.dist-info/RECORD
