Metadata-Version: 2.1
Name: uflux
Version: 0.0.1
Summary: Unified FLUXes (UFLUX)
Home-page: https://github.com/soonyenju/uflux
Author: Songyan Zhu
Author-email: zhusy93@gmail.com
License: MIT Licence
Keywords: Geosciences,geospatial,data science
Platform: any
